ulibrs-0.1.0.dist-info/METADATA
ulibrs-0.1.0.dist-info/WHEEL
ulibrs.libs/libgcc_s-1e52349c.so.1
ulibrs/__init__.py
ulibrs/ulibrs.cpython-311-x86_64-linux-musl.so
ulibrs-0.1.0.dist-info/RECORD
