Metadata-Version: 2.3
Name: ulibrs
Version: 0.1.0
Summary: A simple but universal library written in Rust.
Author: raugfer
License: MIT
Project-URL: Source Code, https://github.com/raugfer/ulibrs
